elyth/__init__.py
elyth/action_executor.py
elyth/bot.py
elyth/context.py
elyth-0.0.0.2.dist-info/licenses/LICENSE
elyth-0.0.0.2.dist-info/METADATA
elyth-0.0.0.2.dist-info/WHEEL
elyth-0.0.0.2.dist-info/top_level.txt
elyth-0.0.0.2.dist-info/RECORD
